{
  "properties": {
    "geometry": {
      "geometries": [
        {
          "type": "Polygon",
          "coordinates": [
            [
              [119, -21],
              [119, -18],
              [114.5, -18],
              [114.5, -21],
              [119, -21]
            ]
          ]
        }
      ],
      "type": "GeometryCollection"
    },
    "status": "completed",
    "contacts": [
      {
        "name": "CSIRO O&A, Information & Data Centre",
        "organization": "CSIRO Oceans & Atmosphere - Hobart",
        "position": "Data Requests",
        "emails": [],
        "addresses": [],
        "links": [],
        "roles": ["pointOfContact", "about"],
        "phones": []
      },
      {
        "name": "Data Officer (AR), Hobart",
        "organization": "CSIRO/Oceans and Atmosphere",
        "position": "",
        "emails": [],
        "addresses": [],
        "links": [],
        "roles": ["processor", "metadata"],
        "phones": []
      },
      {
        "name": "CSIRO O&A, Information & Data Centre",
        "organization": "CSIRO Oceans & Atmosphere - Hobart",
        "position": "Data Requests",
        "emails": [],
        "addresses": [],
        "links": [],
        "roles": ["pointOfContact", "metadata"],
        "phones": []
      }
    ],
    "themes": [
      {
        "scheme": "theme",
        "concepts": [
          {
            "id": "Earth Science | Agriculture | Agricultural Aquatic Sciences | Fisheries",
            "url": "https://marlin.csiro.au/geonetwork/srv/eng/xml.keyword.get?thesaurus=external.theme.gcmd_keywords&id=http://gcmdservices.gsfc.nasa.gov/kms/concept/c7112a64-be39-414a-9125-f63ab44ecb5b",
            "description": "Olsen, L.M., G. Major, K. Shein, J. Scialdone, S. Ritz, T. Stevens, M. Morahan, A. Aleman, R. Vogel, S. Leicester, H. Weir, M. Meaux, S. Grebas, C.Solomon, M. Holland, T. Northcutt, R. A. Restrepo, R. Bilodeau, 2013. NASA/Global Change Master Directory (GCMD) Earth Science Keywords. Version 8.0.0.0.0",
            "title": "GCMD Keywords"
          },
          {
            "id": "Earth Science | Biological Classification | Animals/Invertebrates",
            "url": "https://marlin.csiro.au/geonetwork/srv/eng/xml.keyword.get?thesaurus=external.theme.gcmd_keywords&id=http://gcmdservices.gsfc.nasa.gov/kms/concept/abc6f016-d1f0-4725-b847-639de054d13f",
            "description": "Olsen, L.M., G. Major, K. Shein, J. Scialdone, S. Ritz, T. Stevens, M. Morahan, A. Aleman, R. Vogel, S. Leicester, H. Weir, M. Meaux, S. Grebas, C.Solomon, M. Holland, T. Northcutt, R. A. Restrepo, R. Bilodeau, 2013. NASA/Global Change Master Directory (GCMD) Earth Science Keywords. Version 8.0.0.0.0",
            "title": "GCMD Keywords"
          },
          {
            "id": "Earth Science | Biological Classification | Animals/Vertebrates",
            "url": "https://marlin.csiro.au/geonetwork/srv/eng/xml.keyword.get?thesaurus=external.theme.gcmd_keywords&id=http://gcmdservices.gsfc.nasa.gov/kms/concept/14802b53-b702-438f-8c8a-f51506807ce6",
            "description": "Olsen, L.M., G. Major, K. Shein, J. Scialdone, S. Ritz, T. Stevens, M. Morahan, A. Aleman, R. Vogel, S. Leicester, H. Weir, M. Meaux, S. Grebas, C.Solomon, M. Holland, T. Northcutt, R. A. Restrepo, R. Bilodeau, 2013. NASA/Global Change Master Directory (GCMD) Earth Science Keywords. Version 8.0.0.0.0",
            "title": "GCMD Keywords"
          },
          {
            "id": "Earth Science | Biological Classification | Animals/Vertebrates | Fish",
            "url": "https://marlin.csiro.au/geonetwork/srv/eng/xml.keyword.get?thesaurus=external.theme.gcmd_keywords&id=http://gcmdservices.gsfc.nasa.gov/kms/concept/ea855d4c-f132-44f9-b31c-447e1101684d",
            "description": "Olsen, L.M., G. Major, K. Shein, J. Scialdone, S. Ritz, T. Stevens, M. Morahan, A. Aleman, R. Vogel, S. Leicester, H. Weir, M. Meaux, S. Grebas, C.Solomon, M. Holland, T. Northcutt, R. A. Restrepo, R. Bilodeau, 2013. NASA/Global Change Master Directory (GCMD) Earth Science Keywords. Version 8.0.0.0.0",
            "title": "GCMD Keywords"
          },
          {
            "id": "Earth Science | Biological Classification | Animals/Vertebrates | Fish | Ray-Finned Fishes",
            "url": "https://marlin.csiro.au/geonetwork/srv/eng/xml.keyword.get?thesaurus=external.theme.gcmd_keywords&id=http://gcmdservices.gsfc.nasa.gov/kms/concept/c69cde73-7bd9-489b-a20b-bd23cfb82d92",
            "description": "Olsen, L.M., G. Major, K. Shein, J. Scialdone, S. Ritz, T. Stevens, M. Morahan, A. Aleman, R. Vogel, S. Leicester, H. Weir, M. Meaux, S. Grebas, C.Solomon, M. Holland, T. Northcutt, R. A. Restrepo, R. Bilodeau, 2013. NASA/Global Change Master Directory (GCMD) Earth Science Keywords. Version 8.0.0.0.0",
            "title": "GCMD Keywords"
          },
          {
            "id": "Earth Science | Biosphere | Aquatic Ecosystems | Benthic Habitat",
            "url": "https://marlin.csiro.au/geonetwork/srv/eng/xml.keyword.get?thesaurus=external.theme.gcmd_keywords&id=http://gcmdservices.gsfc.nasa.gov/kms/concept/09a78997-581b-4d1b-ae71-b2b3f96ef719",
            "description": "Olsen, L.M., G. Major, K. Shein, J. Scialdone, S. Ritz, T. Stevens, M. Morahan, A. Aleman, R. Vogel, S. Leicester, H. Weir, M. Meaux, S. Grebas, C.Solomon, M. Holland, T. Northcutt, R. A. Restrepo, R. Bilodeau, 2013. NASA/Global Change Master Directory (GCMD) Earth Science Keywords. Version 8.0.0.0.0",
            "title": "GCMD Keywords"
          },
          {
            "id": "Earth Science | Biosphere | Aquatic Ecosystems | Demersal Habitat",
            "url": "https://marlin.csiro.au/geonetwork/srv/eng/xml.keyword.get?thesaurus=external.theme.gcmd_keywords&id=http://gcmdservices.gsfc.nasa.gov/kms/concept/af953f41-ab6c-4569-9762-c46ad07118da",
            "description": "Olsen, L.M., G. Major, K. Shein, J. Scialdone, S. Ritz, T. Stevens, M. Morahan, A. Aleman, R. Vogel, S. Leicester, H. Weir, M. Meaux, S. Grebas, C.Solomon, M. Holland, T. Northcutt, R. A. Restrepo, R. Bilodeau, 2013. NASA/Global Change Master Directory (GCMD) Earth Science Keywords. Version 8.0.0.0.0",
            "title": "GCMD Keywords"
          },
          {
            "id": "Earth Science | Biosphere | Aquatic Ecosystems | Marine Habitat",
            "url": "https://marlin.csiro.au/geonetwork/srv/eng/xml.keyword.get?thesaurus=external.theme.gcmd_keywords&id=http://gcmdservices.gsfc.nasa.gov/kms/concept/f6350232-b1c7-458c-bc43-bda357ebb6db",
            "description": "Olsen, L.M., G. Major, K. Shein, J. Scialdone, S. Ritz, T. Stevens, M. Morahan, A. Aleman, R. Vogel, S. Leicester, H. Weir, M. Meaux, S. Grebas, C.Solomon, M. Holland, T. Northcutt, R. A. Restrepo, R. Bilodeau, 2013. NASA/Global Change Master Directory (GCMD) Earth Science Keywords. Version 8.0.0.0.0",
            "title": "GCMD Keywords"
          },
          {
            "id": "Earth Science | Biosphere | Aquatic Ecosystems | Pelagic Habitat",
            "url": "https://marlin.csiro.au/geonetwork/srv/eng/xml.keyword.get?thesaurus=external.theme.gcmd_keywords&id=http://gcmdservices.gsfc.nasa.gov/kms/concept/3d7ecc4f-e79e-40d1-8796-63059888bf5f",
            "description": "Olsen, L.M., G. Major, K. Shein, J. Scialdone, S. Ritz, T. Stevens, M. Morahan, A. Aleman, R. Vogel, S. Leicester, H. Weir, M. Meaux, S. Grebas, C.Solomon, M. Holland, T. Northcutt, R. A. Restrepo, R. Bilodeau, 2013. NASA/Global Change Master Directory (GCMD) Earth Science Keywords. Version 8.0.0.0.0",
            "title": "GCMD Keywords"
          },
          {
            "id": "Earth Science | Biosphere | Ecological Dynamics | Community Dynamics | Community Structure",
            "url": "https://marlin.csiro.au/geonetwork/srv/eng/xml.keyword.get?thesaurus=external.theme.gcmd_keywords&id=http://gcmdservices.gsfc.nasa.gov/kms/concept/f42c849c-7113-4c69-a01e-52ebc5e7b44d",
            "description": "Olsen, L.M., G. Major, K. Shein, J. Scialdone, S. Ritz, T. Stevens, M. Morahan, A. Aleman, R. Vogel, S. Leicester, H. Weir, M. Meaux, S. Grebas, C.Solomon, M. Holland, T. Northcutt, R. A. Restrepo, R. Bilodeau, 2013. NASA/Global Change Master Directory (GCMD) Earth Science Keywords. Version 8.0.0.0.0",
            "title": "GCMD Keywords"
          },
          {
            "id": "Earth Science | Biosphere | Ecological Dynamics | Community Dynamics | Species Recruitment",
            "url": "https://marlin.csiro.au/geonetwork/srv/eng/xml.keyword.get?thesaurus=external.theme.gcmd_keywords&id=http://gcmdservices.gsfc.nasa.gov/kms/concept/b98b8823-3e95-4383-bbb0-414ee8832112",
            "description": "Olsen, L.M., G. Major, K. Shein, J. Scialdone, S. Ritz, T. Stevens, M. Morahan, A. Aleman, R. Vogel, S. Leicester, H. Weir, M. Meaux, S. Grebas, C.Solomon, M. Holland, T. Northcutt, R. A. Restrepo, R. Bilodeau, 2013. NASA/Global Change Master Directory (GCMD) Earth Science Keywords. Version 8.0.0.0.0",
            "title": "GCMD Keywords"
          },
          {
            "id": "Earth Science | Biosphere | Ecological Dynamics | Ecosystem Functions | Biomass Dynamics",
            "url": "https://marlin.csiro.au/geonetwork/srv/eng/xml.keyword.get?thesaurus=external.theme.gcmd_keywords&id=http://gcmdservices.gsfc.nasa.gov/kms/concept/a0eb9268-0333-4442-9bc6-efbe338d9836",
            "description": "Olsen, L.M., G. Major, K. Shein, J. Scialdone, S. Ritz, T. Stevens, M. Morahan, A. Aleman, R. Vogel, S. Leicester, H. Weir, M. Meaux, S. Grebas, C.Solomon, M. Holland, T. Northcutt, R. A. Restrepo, R. Bilodeau, 2013. NASA/Global Change Master Directory (GCMD) Earth Science Keywords. Version 8.0.0.0.0",
            "title": "GCMD Keywords"
          },
          {
            "id": "Earth Science | Biosphere | Ecological Dynamics | Ecosystem Functions | Consumption Rates",
            "url": "https://marlin.csiro.au/geonetwork/srv/eng/xml.keyword.get?thesaurus=external.theme.gcmd_keywords&id=http://gcmdservices.gsfc.nasa.gov/kms/concept/d6464d91-2373-456f-85a7-a5019bdb1076",
            "description": "Olsen, L.M., G. Major, K. Shein, J. Scialdone, S. Ritz, T. Stevens, M. Morahan, A. Aleman, R. Vogel, S. Leicester, H. Weir, M. Meaux, S. Grebas, C.Solomon, M. Holland, T. Northcutt, R. A. Restrepo, R. Bilodeau, 2013. NASA/Global Change Master Directory (GCMD) Earth Science Keywords. Version 8.0.0.0.0",
            "title": "GCMD Keywords"
          },
          {
            "id": "Earth Science | Biosphere | Ecological Dynamics | Species/Population Interactions | Survival Rates",
            "url": "https://marlin.csiro.au/geonetwork/srv/eng/xml.keyword.get?thesaurus=external.theme.gcmd_keywords&id=http://gcmdservices.gsfc.nasa.gov/kms/concept/fa68e752-f3a7-4361-a000-47c908545e49",
            "description": "Olsen, L.M., G. Major, K. Shein, J. Scialdone, S. Ritz, T. Stevens, M. Morahan, A. Aleman, R. Vogel, S. Leicester, H. Weir, M. Meaux, S. Grebas, C.Solomon, M. Holland, T. Northcutt, R. A. Restrepo, R. Bilodeau, 2013. NASA/Global Change Master Directory (GCMD) Earth Science Keywords. Version 8.0.0.0.0",
            "title": "GCMD Keywords"
          }
        ]
      },
      {
        "scheme": "equipment",
        "concepts": [
          {
            "id": "Cameras - Still - Underwater",
            "url": "https://marlin.csiro.au/geonetwork/srv/eng/xml.keyword.get?thesaurus=register.equipment.urn:marlin.csiro.au:Equipment&id=urn:marlin.csiro.au:Equipment:concept:28",
            "description": "",
            "title": "CSIRO Equipment"
          },
          {
            "id": "Cameras - Video - Underwater",
            "url": "https://marlin.csiro.au/geonetwork/srv/eng/xml.keyword.get?thesaurus=register.equipment.urn:marlin.csiro.au:Equipment&id=urn:marlin.csiro.au:Equipment:concept:30",
            "description": "",
            "title": "CSIRO Equipment"
          },
          {
            "id": "Demersal Trawls",
            "url": "https://marlin.csiro.au/geonetwork/srv/eng/xml.keyword.get?thesaurus=register.equipment.urn:marlin.csiro.au:Equipment&id=urn:marlin.csiro.au:Equipment:concept:106",
            "description": "",
            "title": "CSIRO Equipment"
          },
          {
            "id": "Midwater Trawls",
            "url": "https://marlin.csiro.au/geonetwork/srv/eng/xml.keyword.get?thesaurus=register.equipment.urn:marlin.csiro.au:Equipment&id=urn:marlin.csiro.au:Equipment:concept:107",
            "description": "",
            "title": "CSIRO Equipment"
          },
          {
            "id": "Trawls",
            "url": "https://marlin.csiro.au/geonetwork/srv/eng/xml.keyword.get?thesaurus=register.equipment.urn:marlin.csiro.au:Equipment&id=urn:marlin.csiro.au:Equipment:concept:104",
            "description": "",
            "title": "CSIRO Equipment"
          }
        ]
      },
      {
        "scheme": "place",
        "concepts": [
          {
            "id": "Marine Features (Australia) | Australian North West Shelf, WA",
            "url": "https://marlin.csiro.au/geonetwork/srv/eng/xml.keyword.get?thesaurus=register.place.urn:aodn.org.au:geographicextents&id=urn:aodn.org.au:geographicextents:concept:65",
            "description": "AODN GEN",
            "title": "AODN Geographic Extent Names"
          }
        ]
      },
      {
        "scheme": "survey",
        "concepts": [
          {
            "id": "Research Voyage: SS 08/95",
            "url": "https://marlin.csiro.au/geonetwork/srv/eng/xml.keyword.get?thesaurus=register.survey.urn:marlin.csiro.au:surveyregister&id=urn:marlin.csiro.au:surveyregister:concept:203",
            "description": "MarLIN Survey Register",
            "title": "CSIRO Survey List"
          }
        ]
      },
      {
        "scheme": "project",
        "concepts": [
          {
            "id": "North West Shelf Demersal Marine Resources Study (1982-1992)",
            "url": "https://marlin.csiro.au/geonetwork/srv/eng/xml.keyword.get?thesaurus=register.project.urn:marlin.csiro.au:projectregister&id=urn:marlin.csiro.au:projectregister:concept:171",
            "description": "MarLIN Project Register",
            "title": "CSIRO Project List"
          }
        ]
      },
      {
        "scheme": "discipline",
        "concepts": [
          {
            "id": "Vessel Data: Catch (by voyage)",
            "url": "https://marlin.csiro.au/geonetwork/srv/eng/xml.keyword.get?thesaurus=register.discipline.urn:marlin.csiro.au:keywords:standardDataType&id=urn:marlin.csiro.au:keywords:standardDataType:concept:3518",
            "description": "MarLIN Standard Datatypes Thesaurus",
            "title": "CSIRO Standard Data Types"
          }
        ]
      },
      {
        "scheme": "dataSource",
        "concepts": [
          {
            "id": "Ship: Southern Surveyor",
            "url": "https://marlin.csiro.au/geonetwork/srv/eng/xml.keyword.get?thesaurus=register.dataSource.urn:marlin.csiro.au:sourceregister&id=urn:marlin.csiro.au:sourceregister:concept:8",
            "description": "MarLIN Source Register",
            "title": "CSIRO Source List"
          }
        ]
      },
      {
        "scheme": "taxon",
        "concepts": [
          {
            "id": "Epinephelus areolatus",
            "url": "https://marlin.csiro.au/geonetwork/srv/eng/xml.keyword.get?thesaurus=register.taxon.urn:lsid:marinespecies.org:taxname&id=urn:lsid:marinespecies.org:taxname:218204",
            "description": "World Register of Marine Species (WoRMS) Taxonomic Names",
            "title": "WoRMS - World Register of Marine Species"
          },
          {
            "id": "Epinephelus multinotatus",
            "url": "https://marlin.csiro.au/geonetwork/srv/eng/xml.keyword.get?thesaurus=register.taxon.urn:lsid:marinespecies.org:taxname&id=urn:lsid:marinespecies.org:taxname:218237",
            "description": "World Register of Marine Species (WoRMS) Taxonomic Names",
            "title": "WoRMS - World Register of Marine Species"
          },
          {
            "id": "Lethrinus genivittatus",
            "url": "https://marlin.csiro.au/geonetwork/srv/eng/xml.keyword.get?thesaurus=register.taxon.urn:lsid:marinespecies.org:taxname&id=urn:lsid:marinespecies.org:taxname:212078",
            "description": "World Register of Marine Species (WoRMS) Taxonomic Names",
            "title": "WoRMS - World Register of Marine Species"
          },
          {
            "id": "Lethrinus nebulosus",
            "url": "https://marlin.csiro.au/geonetwork/srv/eng/xml.keyword.get?thesaurus=register.taxon.urn:lsid:marinespecies.org:taxname&id=urn:lsid:marinespecies.org:taxname:212081",
            "description": "World Register of Marine Species (WoRMS) Taxonomic Names",
            "title": "WoRMS - World Register of Marine Species"
          },
          {
            "id": "Lutjanus malabaricus",
            "url": "https://marlin.csiro.au/geonetwork/srv/eng/xml.keyword.get?thesaurus=register.taxon.urn:lsid:marinespecies.org:taxname&id=urn:lsid:marinespecies.org:taxname:218481",
            "description": "World Register of Marine Species (WoRMS) Taxonomic Names",
            "title": "WoRMS - World Register of Marine Species"
          },
          {
            "id": "Lutjanus sebae",
            "url": "https://marlin.csiro.au/geonetwork/srv/eng/xml.keyword.get?thesaurus=register.taxon.urn:lsid:marinespecies.org:taxname&id=urn:lsid:marinespecies.org:taxname:218499",
            "description": "World Register of Marine Species (WoRMS) Taxonomic Names",
            "title": "WoRMS - World Register of Marine Species"
          },
          {
            "id": "Lutjanus vitta",
            "url": "https://marlin.csiro.au/geonetwork/srv/eng/xml.keyword.get?thesaurus=register.taxon.urn:lsid:marinespecies.org:taxname&id=urn:lsid:marinespecies.org:taxname:218483",
            "description": "World Register of Marine Species (WoRMS) Taxonomic Names",
            "title": "WoRMS - World Register of Marine Species"
          },
          {
            "id": "Nemipterus celebicus",
            "url": "https://marlin.csiro.au/geonetwork/srv/eng/xml.keyword.get?thesaurus=register.taxon.urn:lsid:marinespecies.org:taxname&id=urn:lsid:marinespecies.org:taxname:278121",
            "description": "World Register of Marine Species (WoRMS) Taxonomic Names",
            "title": "WoRMS - World Register of Marine Species"
          },
          {
            "id": "Nemipterus furcosus",
            "url": "https://marlin.csiro.au/geonetwork/srv/eng/xml.keyword.get?thesaurus=register.taxon.urn:lsid:marinespecies.org:taxname&id=urn:lsid:marinespecies.org:taxname:278122",
            "description": "World Register of Marine Species (WoRMS) Taxonomic Names",
            "title": "WoRMS - World Register of Marine Species"
          },
          {
            "id": "Parupeneus heptacanthus",
            "url": "https://marlin.csiro.au/geonetwork/srv/eng/xml.keyword.get?thesaurus=register.taxon.urn:lsid:marinespecies.org:taxname&id=urn:lsid:marinespecies.org:taxname:218657",
            "description": "World Register of Marine Species (WoRMS) Taxonomic Names",
            "title": "WoRMS - World Register of Marine Species"
          },
          {
            "id": "Saurida grandisquamis",
            "url": "https://marlin.csiro.au/geonetwork/srv/eng/xml.keyword.get?thesaurus=register.taxon.urn:lsid:marinespecies.org:taxname&id=urn:lsid:marinespecies.org:taxname:272112",
            "description": "World Register of Marine Species (WoRMS) Taxonomic Names",
            "title": "WoRMS - World Register of Marine Species"
          },
          {
            "id": "Saurida undosquamis",
            "url": "https://marlin.csiro.au/geonetwork/srv/eng/xml.keyword.get?thesaurus=register.taxon.urn:lsid:marinespecies.org:taxname&id=urn:lsid:marinespecies.org:taxname:126371",
            "description": "World Register of Marine Species (WoRMS) Taxonomic Names",
            "title": "WoRMS - World Register of Marine Species"
          }
        ]
      }
    ],
    "citation": {
      "otherConstraints": [
        "Data is made available under a Creative Commons Attribution 4.0 International Licence, please see link. Data is supplied 'as is' without any warranty or guarantee except as required by law to be given to you. The data may not be free of error, comprehensive, current or appropriate for your particular purpose. You accept all risk and responsibility for its use. ATTRIBUTION STATEMENT: The dataset [Insert-dataset-name-here] downloaded on [Insert-DD-Mmm-YYYY-here] was provided by CSIRO."
      ]
    },
    "temporal": [
      {
        "start": "1995-08-18T14:00:00Z",
        "end": "1995-09-09T13:59:59Z"
      }
    ],
    "revision": "2017-06-30T11:40:55",
    "credits": [],
    "license": "Data is made available under a Creative Commons Attribution 4.0 International Licence, please see link. Data is supplied 'as is' without any warranty or guarantee except as required by law to be given to you. The data may not be free of error, comprehensive, current or appropriate for your particular purpose. You accept all risk and responsibility for its use. ATTRIBUTION STATEMENT: The dataset [Insert-dataset-name-here] downloaded on [Insert-DD-Mmm-YYYY-here] was provided by CSIRO.",
    "ai:description": "This record is an overview entry for biological data collected on Southern Surveyor cruise SS 08/95. This cruise took place in the North West Shelf during 18 August - 9 September 1995, under the leadership of Wade Whitelaw. Biological data collected on this cruise include demersal fish and invertebrate samples from 104 stations trawled and 35 mm camera photography of 33 stations trawled. Fish catches were identifed and weighed by species with up to 90 species being caught per half hour trawl. Greatest diversity occurred at the shallower stations. Length frequency data was collected for 14 species of fish (see taxonomy keywords), and otoliths were collected for 4 of the major species (L. sebae, L. choerorynchus, S. undosquamis and N. furcosus). Approximately 50 taxonomic voucher specimens and 100 other specimens were photographed and retained for the Handbook of Australian Seafood, and about 80 specimens and 400 muscle samples were kept for the fillet analysis study. Another 80-90 unidentified specimens were also retained, being mainly deep water species, mustelus species and samples of lizard fish. 6 'fish down' trawl experiments were completed and all fish identified, counted and weighed by species with 30 stomachs collected from Lethrinus genivittatus, L. choerorynchus, Memipterus furcosus and Saurida undosquamis. Video photography and 35 mm camera photography of the trawls were also obtained. 3 hydrographic transects were completed with the sumbersible data logger (SDL) and over 195 species of sponges for taxonomic studies by the Queensland Museum were collected. 125 humpback whales and 8 unidentified cetaceans and approximately 120 dophins were also observed during the cruise. Please note: This metadata record is a preliminary entry derived from information in the cruise plan and/or cruise report. Individual data types - which may span several cruises - will be indexed separately within this metadata system in due course. - Biological Field Data Sheets recorded during this voyage have been scanned to PDF, and are available (to CSIRO Staff) on-line. See the details link under \"Stored Media List\" (below).",
    "centroid": [[116.63, -19.37]],
    "statement": "Data source: original field data."
  },
  "id": "02077f4e-395c-4f6c-b85d-fd934788a5ae",
  "title": "Southern Surveyor Voyage SS 08/95 Biological Data Overview",
  "description": "This record is an overview entry for biological data collected on Southern Surveyor cruise SS 08/95. This cruise took place in the North West Shelf during 18 August - 9 September 1995, under the leadership of Wade Whitelaw. Biological data collected on this cruise include demersal fish and invertebrate samples from 104 stations trawled and 35 mm camera photography of 33 stations trawled. Fish catches were identifed and weighed by species with up to 90 species being caught per half hour trawl. Greatest diversity occurred at the shallower stations. Length frequency data was collected for 14 species of fish (see taxonomy keywords), and otoliths were collected for 4 of the major species (L. sebae, L. choerorynchus, S. undosquamis and N. furcosus). Approximately 50 taxonomic voucher specimens and 100 other specimens were photographed and retained for the Handbook of Australian Seafood, and about 80 specimens and 400 muscle samples were kept for the fillet analysis study. Another 80-90 unidentified specimens were also retained, being mainly deep water species, mustelus species and samples of lizard fish. 6 'fish down' trawl experiments were completed and all fish identified, counted and weighed by species with 30 stomachs collected from Lethrinus genivittatus, L. choerorynchus, Memipterus furcosus and Saurida undosquamis. Video photography and 35 mm camera photography of the trawls were also obtained. 3 hydrographic transects were completed with the sumbersible data logger (SDL) and over 195 species of sponges for taxonomic studies by the Queensland Museum were collected. 125 humpback whales and 8 unidentified cetaceans and approximately 120 dophins were also observed during the cruise. Please note: This metadata record is a preliminary entry derived from information in the cruise plan and/or cruise report. Individual data types - which may span several cruises - will be indexed separately within this metadata system in due course. - Biological Field Data Sheets recorded during this voyage have been scanned to PDF, and are available (to CSIRO Staff) on-line. See the details link under \"Stored Media List\" (below).",
  "links": [
    {
      "href": "https://www.cmar.csiro.au/geoserver/wms?&CQL_FILTER=SURVEY_NAME%20%3D%20%27SS199508%27",
      "rel": "wms",
      "type": "",
      "title": "cmar:CATCH_HEADER_AODN_VIEW[Catch data for Southern Surveyor Voyage SS 08/95]",
      "ai:group": "Data Access > wms"
    },
    {
      "href": "https://www.marine.csiro.au/datacentre/projects/BioData/PDFs/BOX_AB2009_1426/BOX_AB2009_1426_index.htm",
      "rel": "data",
      "type": "",
      "title": "Stored Media List (CSIRO internal use only)[Biological Field Data Sheets - 1988 GAB Survey - RV Southern Surveyor - various Plans and Summaries plus SS 8/95 (1988 - 1995) as PDF (Item ref: AB2009_1426 PDFs)]",
      "ai:group": "Document"
    },
    {
      "href": "https://www.marine.csiro.au/data/trawler/dataset.cfm?survey=SS199508&data_type=catch",
      "rel": "data",
      "type": "",
      "title": "Data Link[Data available via Data Trawler]",
      "ai:group": "Data Access"
    },
    {
      "href": "https://www.marine.csiro.au/data/trawler/survey_list.cfm?source_id=8",
      "rel": "related",
      "type": "text/html",
      "title": "Data Link[RV Southern Surveyor Survey Information including voyage plans and summaries]",
      "ai:group": "Data Access"
    },
    {
      "href": "https://www.marine.csiro.au/data/trawler/download.cfm?file_id=18",
      "rel": "related",
      "type": "text/html",
      "title": "Documentation Link[Catch Composition Data (pdf)]",
      "ai:group": "Document"
    },
    {
      "href": "https://www.marine.csiro.au/data/trawler/download.cfm?file_id=19",
      "rel": "related",
      "type": "text/html",
      "title": "Documentation Link[Deck Logs (pdf)]",
      "ai:group": "Document"
    },
    {
      "href": "https://www.marine.csiro.au/data/trawler/download.cfm?file_id=20",
      "rel": "related",
      "type": "text/html",
      "title": "Documentation Link[Field Biological Data (pdf)]",
      "ai:group": "Document"
    },
    {
      "href": "https://mnf.csiro.au/",
      "rel": "related",
      "type": "text/html",
      "title": "Documentation Link[Marine National Facility]",
      "ai:group": "Document"
    },
    {
      "href": "https://www.marine.csiro.au/data/trawler/download.cfm?file_id=21",
      "rel": "related",
      "type": "text/html",
      "title": "Documentation Link[Station Logs (pdf)]",
      "ai:group": "Document"
    },
    {
      "href": "https://creativecommons.org/licenses/by/4.0/",
      "rel": "related",
      "type": "text/html",
      "title": "Documentation Link[This work is licensed under a Creative Commons Attribution 4.0 International License]",
      "ai:group": "Document"
    },
    {
      "href": "https://geonetwork-edge.edge.aodn.org.au:443/geonetwork/images/logos/58d5af30-fbc6-42dc-8971-5468df74e9ee.png",
      "rel": "icon",
      "type": "image/png",
      "title": "Suggest icon for dataset"
    },
    {
      "href": "https://www.cmar.csiro.au/data/trawler/dataset_mapfile.cfm?survey=SS199508&data_type=catch&img_type=tn",
      "rel": "preview",
      "type": "image"
    }
  ],
  "extent": {
    "spatial": {
      "bbox": [
        [114.5, -21.0, 119.0, -18.0],
        [114.5, -21.0, 119.0, -18.0]
      ],
      "crs": "http://www.opengis.net/def/crs/OGC/1.3/CRS84"
    },
    "temporal": {
      "interval": [
        ["1995-08-18T14:00:00.000+00:00", "1995-09-09T13:59:59.000+00:00"],
        ["1995-08-18T14:00:00.000+00:00", "1995-09-09T13:59:59.000+00:00"]
      ],
      "trs": "http://www.opengis.net/def/uom/ISO-8601/0/Gregorian"
    }
  },
  "itemType": "Collection"
}
